daTree/ClassificationTree.py
daTree/__init__.py
daTree-0.1.0.dist-info/LICENSE.txt
daTree-0.1.0.dist-info/METADATA
daTree-0.1.0.dist-info/WHEEL
daTree-0.1.0.dist-info/top_level.txt
daTree-0.1.0.dist-info/RECORD
