Metadata-Version: 2.1
Name: daTree
Version: 0.1.0
Summary: with this package you can create data-based decision trees manually, semi-automatically, or automatically
Home-page: https://github.com/dein_github/my_library
Author: Yannik Fleischer
Author-email: yanflei@math.uni-paderborn.de
Classifier: Programming Language :: Python :: 3
Classifier: License :: OSI Approved :: MIT License
Classifier: Operating System :: OS Independent
Requires-Python: >=3.6
License-File: LICENSE.txt
Requires-Dist: numpy (==1.21.5)
Requires-Dist: pandas (==1.4.4)
Requires-Dist: graphviz (==0.20.1)
